devpi_semantic_ui/__about__.py
devpi_semantic_ui/__init__.py
devpi_semantic_ui/views.py
devpi_semantic_ui/static/devpi-semantic.css
devpi_semantic_ui/static/devpi-semantic.js
devpi_semantic_ui/static/pygments.css
devpi_semantic_ui/static/semantic.min.css
devpi_semantic_ui/static/semantic.min.js
devpi_semantic_ui/static/images/python-logo.svg
devpi_semantic_ui/static/images/python.svg
devpi_semantic_ui/static/themes/default/assets/fonts/icons.eot
devpi_semantic_ui/static/themes/default/assets/fonts/icons.otf
devpi_semantic_ui/static/themes/default/assets/fonts/icons.svg
devpi_semantic_ui/static/themes/default/assets/fonts/icons.ttf
devpi_semantic_ui/static/themes/default/assets/fonts/icons.woff
devpi_semantic_ui/static/themes/default/assets/fonts/icons.woff2
devpi_semantic_ui/static/themes/default/assets/images/flags.png
devpi_semantic_ui/templates/doc.pt
devpi_semantic_ui/templates/error.pt
devpi_semantic_ui/templates/index.pt
devpi_semantic_ui/templates/layout.pt
devpi_semantic_ui/templates/macros.pt
devpi_semantic_ui/templates/notfound.pt
devpi_semantic_ui/templates/project.pt
devpi_semantic_ui/templates/root.pt
devpi_semantic_ui/templates/search.pt
devpi_semantic_ui/templates/search_help.pt
devpi_semantic_ui/templates/status.pt
devpi_semantic_ui/templates/toxresult.pt
devpi_semantic_ui/templates/toxresults.pt
devpi_semantic_ui/templates/version.pt
devpi_semantic_ui-0.2.2.dist-info/DESCRIPTION.rst
devpi_semantic_ui-0.2.2.dist-info/METADATA
devpi_semantic_ui-0.2.2.dist-info/RECORD
devpi_semantic_ui-0.2.2.dist-info/WHEEL
devpi_semantic_ui-0.2.2.dist-info/entry_points.txt
devpi_semantic_ui-0.2.2.dist-info/metadata.json
devpi_semantic_ui-0.2.2.dist-info/top_level.txt
