Metadata-Version: 2.0
Name: devpi-semantic-ui
Version: 0.2.2
Summary: A Semantic UI theme for devpi
Home-page: https://github.com/apihackers/devpi-semantic-ui
Author: API Hackers
Author-email: github@apihackers.com
License: MIT
Keywords: devpi semantic-ui
Platform: UNKNOWN
Classifier: Development Status :: 3 - Alpha
Classifier: Programming Language :: Python
Classifier: Environment :: Web Environment
Classifier: Operating System :: OS Independent
Classifier: Intended Audience :: Developers
Classifier: Topic :: System :: Software Distribution
Classifier: Programming Language :: Python
Classifier: Programming Language :: Python :: 3
Classifier: Programming Language :: Python :: 3.3
Classifier: Programming Language :: Python :: 3.4
Classifier: Programming Language :: Python :: 3.5
Classifier: Topic :: Software Development :: Libraries :: Python Modules
Classifier: License :: OSI Approved :: MIT License
Requires-Dist: devpi-web
